django_app_requires/__init__.py
django_app_requires/utils.py
django_app_requires-0.3.6.dist-info/licenses/LICENSE
django_app_requires_first_placeholder/__init__.py
django_app_requires_first_placeholder/admin.py
django_app_requires_first_placeholder/apps.py
django_app_requires_first_placeholder/models.py
django_app_requires_first_placeholder/tests.py
django_app_requires_first_placeholder/views.py
django_app_requires_first_placeholder/migrations/__init__.py
django_app_requires_last_placeholder/__init__.py
django_app_requires_last_placeholder/admin.py
django_app_requires_last_placeholder/apps.py
django_app_requires_last_placeholder/models.py
django_app_requires_last_placeholder/tests.py
django_app_requires_last_placeholder/views.py
django_app_requires_last_placeholder/migrations/__init__.py
django_app_requires-0.3.6.dist-info/METADATA
django_app_requires-0.3.6.dist-info/WHEEL
django_app_requires-0.3.6.dist-info/top_level.txt
django_app_requires-0.3.6.dist-info/RECORD
