Metadata-Version: 2.4
Name: django-app-requires
Version: 0.3.6
Summary: A simple Django app that allows you to specify app dependencies and middleware dependencies in your own apps, and also add defaults for additional configurations.
Author: rRR0VrFP
Maintainer: rRR0VrFP
License: MIT
Keywords: django utils
Classifier: Development Status :: 5 - Production/Stable
Classifier: Intended Audience :: Developers
Classifier: Topic :: Software Development :: Libraries :: Python Modules
Classifier: License :: OSI Approved :: MIT License
Classifier: Programming Language :: Python :: 3
Classifier: Programming Language :: Python :: 3 :: Only
License-File: LICENSE
Requires-Dist: django
Requires-Dist: zenutils
Dynamic: author
Dynamic: classifier
Dynamic: description
Dynamic: description-content-type
Dynamic: keywords
Dynamic: license
Dynamic: license-file
Dynamic: maintainer
Dynamic: requires-dist
Dynamic: summary
